aegea/__init__.py
aegea/aegea_config.py
aegea/alarms.py
aegea/audit.py
aegea/base_config.yml
aegea/batch.py
aegea/billing.py
aegea/build_ami.py
aegea/build_docker_image.py
aegea/cloudtrail.py
aegea/constants.json
aegea/cost.py
aegea/ebs.py
aegea/ecr.py
aegea/ecs.py
aegea/efs.py
aegea/elb.py
aegea/flow_logs.py
aegea/iam.py
aegea/instance_ctl.py
aegea/lambda.py
aegea/launch.py
aegea/logs.py
aegea/ls.py
aegea/pricing.py
aegea/rds.py
aegea/rm.py
aegea/s3.py
aegea/secrets.py
aegea/sfn.py
aegea/ssh.py
aegea/top.py
aegea/user_config.yml
aegea/version.py
aegea/zones.py
aegea/missions/.gitignore
aegea/missions/arvados/Makefile
aegea/missions/arvados/config.yml
aegea/missions/arvados/deploy-arvados.sh
aegea/missions/arvados/environment
aegea/missions/arvados/rootfs.skel.in/etc/fuse.conf
aegea/missions/arvados/rootfs.skel.in/etc/keep.conf.json
aegea/missions/arvados/rootfs.skel.in/etc/arvados/api/application.yml
aegea/missions/arvados/rootfs.skel.in/etc/arvados/api/database.yml
aegea/missions/arvados/rootfs.skel.in/etc/arvados/crunch-dispatch-slurm/crunch-dispatch-slurm.yml
aegea/missions/arvados/rootfs.skel.in/etc/arvados/docker-cleaner/docker-cleaner.json
aegea/missions/arvados/rootfs.skel.in/etc/arvados/keep-web/keep-web.yml
aegea/missions/arvados/rootfs.skel.in/etc/arvados/keepproxy/keepproxy.yml
aegea/missions/arvados/rootfs.skel.in/etc/arvados/nodemanager/ec2.cfg
aegea/missions/arvados/rootfs.skel.in/etc/arvados/sso/application.yml
aegea/missions/arvados/rootfs.skel.in/etc/arvados/sso/database.yml
aegea/missions/arvados/rootfs.skel.in/etc/arvados/sso/production.rb
aegea/missions/arvados/rootfs.skel.in/etc/arvados/workbench/application.yml
aegea/missions/arvados/rootfs.skel.in/etc/default/munge
aegea/missions/arvados/rootfs.skel.in/etc/init/arvados-api.conf
aegea/missions/arvados/rootfs.skel.in/etc/init/arvados-keep.conf
aegea/missions/arvados/rootfs.skel.in/etc/init/arvados-keepproxy.conf
aegea/missions/arvados/rootfs.skel.in/etc/init/arvados-keepweb.conf
aegea-4.5.2.dist-info/licenses/LICENSE.md
aegea-4.5.2.dist-info/METADATA
aegea-4.5.2.dist-info/WHEEL
aegea-4.5.2.dist-info/top_level.txt
aegea-4.5.2.dist-info/RECORD
