Metadata-Version: 2.4
Name: aegea
Version: 4.5.2
Summary: Amazon Web Services Operator Interface
Home-page: https://github.com/kislyuk/aegea
Author: Andrey Kislyuk
Author-email: kislyuk@gmail.com
License: Apache Software License
Platform: MacOS X
Platform: Posix
License-File: LICENSE.md
Requires-Dist: boto3<2,>=1.34.46
Requires-Dist: argcomplete<4,>=3.1.4
Requires-Dist: paramiko<4,>=2.12.0
Requires-Dist: requests<3,>=2.31.0
Requires-Dist: tweak<2,>=1.0.4
Requires-Dist: pyyaml<7,>=6.0.1
Requires-Dist: python-dateutil<3,>=2.8.2
Requires-Dist: babel<3,>=2.10.3
Requires-Dist: ipwhois<2,>=1.2.0
Requires-Dist: uritemplate<5,>=4.1.1
Requires-Dist: certifi>=2023.11.17
Provides-Extra: test
Requires-Dist: coverage; extra == "test"
Requires-Dist: wheel; extra == "test"
Requires-Dist: ruff; extra == "test"
Requires-Dist: mypy; extra == "test"
Requires-Dist: types-python-dateutil; extra == "test"
Requires-Dist: types-requests; extra == "test"
Requires-Dist: types-PyYAML; extra == "test"
Provides-Extra: batch
Requires-Dist: chalice; extra == "batch"
Dynamic: author
Dynamic: author-email
Dynamic: description
Dynamic: home-page
Dynamic: license
Dynamic: license-file
Dynamic: platform
Dynamic: provides-extra
Dynamic: requires-dist
Dynamic: summary
